feon_dynamic/__init__.py
feon_dynamic/core.py
feon_dynamic/data/K_dict.pkl.gz
feon_dynamic/data/positions.xlsx
feon_dynamic-1.0.1.dist-info/METADATA
feon_dynamic-1.0.1.dist-info/WHEEL
feon_dynamic-1.0.1.dist-info/top_level.txt
feon_dynamic-1.0.1.dist-info/RECORD
